vectors/__init__.py
vectors/math2.py
kaiservector-0.0.1.dist-info/METADATA
kaiservector-0.0.1.dist-info/WHEEL
kaiservector-0.0.1.dist-info/top_level.txt
kaiservector-0.0.1.dist-info/RECORD
