Metadata-Version: 2.1
Name: kaiservector
Version: 0.0.1
Summary: Impliments Vector Math
Author: Kaiser Fechner
Author-email: <coolpotatorocks@gmail.com>
Keywords: python,vector,math
Classifier: Development Status :: 1 - Planning
Classifier: Intended Audience :: Developers
Classifier: Programming Language :: Python :: 3
Classifier: Operating System :: Unix
Classifier: Operating System :: MacOS :: MacOS X
Classifier: Operating System :: Microsoft :: Windows
